{
  "swagger": "2.0",
  "info": {
    "title": "Users API",
    "version": "1.0.0",
    "description": "Users API"
  },
  "host": "localhost:3000",
  "basePath": "/api/users",
  "schemes": [
    "http"
  ],
  "paths": {
    "/": {
      "get": {
        "description": "Returns all users",
        "responses": {
          "200": {
            "description": "OK"
          }
        }
      },
      "post": {
        "description": "Creates a new user",
        "responses": {
          "200": {
            "description": "OK"
          }
        }
      }
    }
  }
}